{
  "news": [
    {
      "id": 1,
      "title": "Бакметрополитен о сроках сдачи в эксплуатацию новой станции",
      "published": "2020-09-14T11:13:00.000Z"
    },
    {
      "id": 2,
      "title": "Самед Сеидов: Армяне уклонились от обсуждений незаконного заселения Нагорного Карабаха в комитетах ПАСЕ",
      "published": "2020-09-14T10:31:00.000Z"
    },
    {
      "id": 3,
      "title": "Фарид Шафиев: Русскоязычные школы могут перейти на систему двуязычного образования",
      "published": "2020-09-14T10:16:03.000Z"
    },
    {
      "id": 4,
      "title": "Самед Сеидов: В будущем визовый режим с Турцией может быть полностью отменен",
      "published": "2020-09-14T09:07:00.000Z"
    },
    {
      "id": 5,
      "title": "Армения вновь пытается обострить ситуацию на границе с Азербайджаном",
      "published": "2020-09-14T08:24:00.000Z"
    }
  ]
}